pyodi/__init__.py
pyodi/cli.py
pyodi/apps/__init__.py
pyodi/apps/evaluation.py
pyodi/apps/ground_truth.py
pyodi/apps/paint_annotations.py
pyodi/apps/coco/__init__.py
pyodi/apps/coco/coco_merge.py
pyodi/apps/coco/coco_split.py
pyodi/apps/crops/__init__.py
pyodi/apps/crops/crops_merge.py
pyodi/apps/crops/crops_split.py
pyodi/apps/train_config/__init__.py
pyodi/apps/train_config/train_config_evaluation.py
pyodi/apps/train_config/train_config_generation.py
pyodi/core/__init__.py
pyodi/core/anchor_generator.py
pyodi/core/boxes.py
pyodi/core/clustering.py
pyodi/core/crops.py
pyodi/core/nms.py
pyodi/core/utils.py
pyodi/plots/__init__.py
pyodi/plots/boxes.py
pyodi/plots/clustering.py
pyodi/plots/common.py
pyodi/plots/evaluation.py
pyodi-0.0.9.dist-info/LICENSE
pyodi-0.0.9.dist-info/METADATA
pyodi-0.0.9.dist-info/WHEEL
pyodi-0.0.9.dist-info/entry_points.txt
pyodi-0.0.9.dist-info/top_level.txt
pyodi-0.0.9.dist-info/RECORD
