Metadata-Version: 2.1
Name: pyodi
Version: 0.0.9
Summary: Object Detection Insights
Home-page: https://github.com/Gradiant/pyodi
Author: Pyodi
License: UNKNOWN
Platform: UNKNOWN
Requires-Python: >=3.8
Requires-Dist: numpy (==1.22.1)
Requires-Dist: loguru (==0.6.0)
Requires-Dist: matplotlib (==3.5.2)
Requires-Dist: numba (>=0.56.0)
Requires-Dist: pandas (==1.4.2)
Requires-Dist: pillow (==9.2.0)
Requires-Dist: plotly (==5.9.0)
Requires-Dist: pycocotools (==2.0.4)
Requires-Dist: kaleido (==v0.2.1)
Requires-Dist: scikit-learn (==1.1.1)
Requires-Dist: fire (==0.4.0)
Provides-Extra: dev
Requires-Dist: black (==22.6.0) ; extra == 'dev'
Requires-Dist: flake8 (==4.0.1) ; extra == 'dev'
Requires-Dist: flake8-docstrings (==1.6.0) ; extra == 'dev'
Requires-Dist: isort (==5.10.1) ; extra == 'dev'
Requires-Dist: mkdocs (==1.3.1) ; extra == 'dev'
Requires-Dist: mkdocstrings (==0.19.0) ; extra == 'dev'
Requires-Dist: mkdocs-material (==8.3.9) ; extra == 'dev'
Requires-Dist: mkdocstrings-python (==0.7.1) ; extra == 'dev'
Requires-Dist: mock (==4.0.3) ; extra == 'dev'
Requires-Dist: mypy (==0.960) ; extra == 'dev'
Requires-Dist: pre-commit (==2.20.0) ; extra == 'dev'
Requires-Dist: pydocstyle (==6.1.1) ; extra == 'dev'
Requires-Dist: pymdown-extensions (==9.5) ; extra == 'dev'
Requires-Dist: pytest (==7.1.2) ; extra == 'dev'
